MANIFEST.in
README.rst
setup.py
daddy_avatar/__init__.py
daddy_avatar/models.py
daddy_avatar/tests.py
daddy_avatar/views.py
daddy_avatar/templatetags/__init__.py
daddy_avatar/templatetags/__init__.pyc
daddy_avatar/templatetags/daddy_avatar.py
daddy_avatar/templatetags/daddy_avatar.pyc
django_daddy_avatar.egg-info/PKG-INFO
django_daddy_avatar.egg-info/SOURCES.txt
django_daddy_avatar.egg-info/dependency_links.txt
django_daddy_avatar.egg-info/not-zip-safe
django_daddy_avatar.egg-info/top_level.txt