Metadata-Version: 1.1
Name: django-daddy-avatar
Version: 1.0.3
Summary: very simple avatar from gravatar
Home-page: https://github.com/karoon/django-daddy-avatar
Author: vahid chakoshy
Author-email: vchakoshy@gmail.com
License: UNKNOWN
Platform: UNKNOWN
Classifier: Framework :: Django
Classifier: Intended Audience :: Developers
Classifier: License :: OSI Approved :: BSD License
Classifier: Operating System :: OS Independent
Classifier: Programming Language :: Python
Classifier: Topic :: Internet :: WWW/HTTP
Classifier: Natural Language :: Persian
